ltp_extension-0.1.13.dist-info/METADATA
ltp_extension-0.1.13.dist-info/WHEEL
ltp_extension-0.1.13.dist-info/license_files/LICENSE
ltp_extension/__init__.py
ltp_extension/algorithms/__init__.py
ltp_extension/algorithms/algorithms.pyi
ltp_extension/ltp_extension.pyi
ltp_extension/perceptron/__init__.py
ltp_extension/perceptron/perceptron.pyi
ltp_extension/ltp_extension.abi3.so
ltp_extension-0.1.13.dist-info/RECORD
