Metadata-Version: 2.3
Name: ltp-extension
Version: 0.1.13
License-File: LICENSE
Summary: Rust Extension For Language Technology Platform(Python).
Keywords: ltp,nlp
Home-Page: https://github.com/HIT-SCIR/ltp
Author: ylfeng <ylfeng@ir.hit.edu.cn>
Author-email: ylfeng <ylfeng@ir.hit.edu.cn>
Project-URL: Source Code, https://github.com/HIT-SCIR/ltp
